{
  "swagger": "2.0",
  "info": {
    "title": "My API",
    "description": "Temple API",
    "version": "1.0.0"
  },
  "host": "cse-341-the-web-service-1.onrender.com",
  "basePath": "/",
  "schemes": [
    "https"
  ],
  "paths": {
    "/": {
      "get": {
        "description": "",
        "responses": {
          "200": {
            "description": "OK"
          }
        }
      }
    },
    "/api-docs": {
      "get": {
        "description": "",
        "responses": {
          "default": {
            "description": ""
          }
        }
      }
    },
    "/songs/": {
      "get": {
        "tags": [
          "Songs"
        ],
        "description": "",
        "produces": [
          "application/json"
        ],
        "responses": {
          "200": {
            "description": "OK"
          }
        }
      },
      "post": {
        "tags": [
          "Songs"
        ],
        "description": "",
        "parameters": [
          {
            "name": "body",
            "in": "body",
            "schema": {
              "type": "object",
              "properties": {
                "NameSong": {
                  "example": "any"
                },
                "Author": {
                  "example": "any"
                },
                "duration": {
                  "example": "any"
                },
                "releaseDate": {
                  "example": "any"
                },
                "genre": {
                  "example": "any"
                },
                "language": {
                  "example": "any"
                },
                "album": {
                  "example": "any"
                }
              }
            }
          }
        ],
        "responses": {
          "204": {
            "description": "No Content"
          },
          "412": {
            "description": "Precondition Failed"
          },
          "500": {
            "description": "Internal Server Error"
          }
        }
      }
    },
    "/songs/{id}": {
      "get": {
        "tags": [
          "Songs"
        ],
        "description": "",
        "produces": [
          "application/json"
        ],
        "parameters": [
          {
            "name": "id",
            "in": "path",
            "required": true,
            "type": "string"
          }
        ],
        "responses": {
          "200": {
            "description": "OK"
          },
          "400": {
            "description": "Bad Request"
          }
        }
      },
      "put": {
        "tags": [
          "Songs"
        ],
        "description": "",
        "parameters": [
          {
            "name": "id",
            "in": "path",
            "required": true,
            "type": "string"
          },
          {
            "name": "body",
            "in": "body",
            "schema": {
              "type": "object",
              "properties": {
                "NameSong": {
                  "example": "any"
                },
                "Author": {
                  "example": "any"
                },
                "duration": {
                  "example": "any"
                },
                "releaseDate": {
                  "example": "any"
                },
                "genre": {
                  "example": "any"
                },
                "language": {
                  "example": "any"
                },
                "album": {
                  "example": "any"
                }
              }
            }
          }
        ],
        "responses": {
          "204": {
            "description": "No Content"
          },
          "400": {
            "description": "Bad Request"
          },
          "412": {
            "description": "Precondition Failed"
          },
          "500": {
            "description": "Internal Server Error"
          }
        }
      },
      "delete": {
        "tags": [
          "Songs"
        ],
        "description": "",
        "parameters": [
          {
            "name": "id",
            "in": "path",
            "required": true,
            "type": "string"
          }
        ],
        "responses": {
          "204": {
            "description": "No Content"
          },
          "400": {
            "description": "Bad Request"
          },
          "500": {
            "description": "Internal Server Error"
          }
        }
      }
    },
    "/books/": {
      "get": {
        "tags": [
          "Books"
        ],
        "description": "",
        "produces": [
          "application/json"
        ],
        "responses": {
          "200": {
            "description": "OK"
          }
        }
      },
      "post": {
        "tags": [
          "Books"
        ],
        "description": "",
        "parameters": [
          {
            "name": "body",
            "in": "body",
            "schema": {
              "type": "object",
              "properties": {
                "NameBook": {
                  "example": "any"
                },
                "Author": {
                  "example": "any"
                },
                "Pages": {
                  "example": "any"
                }
              }
            }
          }
        ],
        "responses": {
          "204": {
            "description": "No Content"
          },
          "412": {
            "description": "Precondition Failed"
          },
          "500": {
            "description": "Internal Server Error"
          }
        }
      }
    },
    "/books/{id}": {
      "get": {
        "tags": [
          "Books"
        ],
        "description": "",
        "produces": [
          "application/json"
        ],
        "parameters": [
          {
            "name": "id",
            "in": "path",
            "required": true,
            "type": "string"
          }
        ],
        "responses": {
          "200": {
            "description": "OK"
          },
          "400": {
            "description": "Bad Request"
          }
        }
      },
      "put": {
        "tags": [
          "Books"
        ],
        "description": "",
        "parameters": [
          {
            "name": "id",
            "in": "path",
            "required": true,
            "type": "string"
          },
          {
            "name": "body",
            "in": "body",
            "schema": {
              "type": "object",
              "properties": {
                "NameBook": {
                  "example": "any"
                },
                "Author": {
                  "example": "any"
                },
                "Pages": {
                  "example": "any"
                }
              }
            }
          }
        ],
        "responses": {
          "204": {
            "description": "No Content"
          },
          "400": {
            "description": "Bad Request"
          },
          "412": {
            "description": "Precondition Failed"
          },
          "500": {
            "description": "Internal Server Error"
          }
        }
      },
      "delete": {
        "tags": [
          "Books"
        ],
        "description": "",
        "parameters": [
          {
            "name": "id",
            "in": "path",
            "required": true,
            "type": "string"
          }
        ],
        "responses": {
          "204": {
            "description": "No Content"
          },
          "400": {
            "description": "Bad Request"
          },
          "500": {
            "description": "Internal Server Error"
          }
        }
      }
    }
  }
}